bpm_ai/__init__.py
bpm_ai/common/__init__.py
bpm_ai/common/errors.py
bpm_ai/common/multimodal.py
bpm_ai/compose/__init__.py
bpm_ai/compose/compose.anthropic.prompt
bpm_ai/compose/compose.openai.prompt
bpm_ai/compose/compose.prompt
bpm_ai/compose/compose.py
bpm_ai/compose/util.py
bpm_ai/decide/__init__.py
bpm_ai/decide/decide.anthropic.prompt
bpm_ai/decide/decide.openai.prompt
bpm_ai/decide/decide.prompt
bpm_ai/decide/decide.py
bpm_ai/decide/schema.py
bpm_ai/extract/__init__.py
bpm_ai/extract/extract.anthropic.prompt
bpm_ai/extract/extract.openai.prompt
bpm_ai/extract/extract.prompt
bpm_ai/extract/extract.py
bpm_ai/extract/util.py
bpm_ai/generic/__init__.py
bpm_ai/generic/generic.anthropic.prompt
bpm_ai/generic/generic.openai.prompt
bpm_ai/generic/generic.prompt
bpm_ai/generic/generic.py
bpm_ai/retrieval/__init__.py
bpm_ai/retrieval/answer_synthesis.prompt
bpm_ai/retrieval/final_synthesis.prompt
bpm_ai/retrieval/query_strategy.prompt
bpm_ai/retrieval/query_strategy_1.prompt
bpm_ai/retrieval/retrieval.py
bpm_ai/retrieval/util.py
bpm_ai/translate/__init__.py
bpm_ai/translate/translate.anthropic.prompt
bpm_ai/translate/translate.openai.prompt
bpm_ai/translate/translate.prompt
bpm_ai/translate/translate.py
bpm_ai/translate/util.py
bpm_ai-1.7.4.dist-info/METADATA
bpm_ai-1.7.4.dist-info/WHEEL
bpm_ai-1.7.4.dist-info/RECORD
